VGA/Consts.py
VGA/DrawMol.py
VGA/Error.py
VGA/__init__.py
VGA/GroupAdd/DataDir.py
VGA/GroupAdd/FindResStruc.py
VGA/GroupAdd/Group.py
VGA/GroupAdd/Library.py
VGA/GroupAdd/Scheme.py
VGA/GroupAdd/__init__.py
VGA/RDkitWrapper/GenRxnNet.py
VGA/RDkitWrapper/MolQuery.py
VGA/RDkitWrapper/ReactionQuery.py
VGA/RDkitWrapper/__init__.py
VGA/RINGParser/Grammar.py
VGA/RINGParser/MolQueryRead.py
VGA/RINGParser/Parser.py
VGA/RINGParser/ReactionQueryRead.py
VGA/RINGParser/Reader.py
VGA/RINGParser/__init__.py
VGA/ThermoChem/__init__.py
VGA/ThermoChem/base.py
VGA/ThermoChem/group_data.py
VGA/ThermoChem/incomplete.py
VGA/ThermoChem/raw_data.py
VGA/Units/__init__.py
VGA/Units/builtin.py
VGA/Units/db.py
VGA/Units/helpers.py
VGA/Units/parser.py
VGA/Units/qty.py
VGA/Units/utils.py
VGA/data/BensonGA/library.yaml
VGA/data/BensonGA/scheme.yaml
VGA/data/BensonGA/surface_benson.lib.yaml
VGA/data/BensonGA/gas_benson/corrections.yaml
VGA/data/BensonGA/gas_benson/extra.yaml
VGA/data/BensonGA/gas_benson/hydrocarbons.yaml
VGA/data/BensonGA/gas_benson/hydrocarbons_original.yaml
VGA/data/BensonGA/gas_benson/index.yaml
VGA/data/BensonGA/gas_benson/nitrogenates.yaml
VGA/data/BensonGA/gas_benson/original.yaml
VGA/data/BensonGA/gas_benson/oxygenates.yaml
VGA/data/BensonGA/gas_benson/radicals.yaml
VGA/data/BensonGA/gas_benson/strain.yaml
VGA/data/GRWAqueous2018/library.yaml
VGA/data/GRWAqueous2018/scheme.yaml
VGA/data/GRWAqueous2018/surface.yaml
VGA/data/GRWAqueous2018/uq.yaml
VGA/data/GRWSurface2018/library.yaml
VGA/data/GRWSurface2018/scheme.yaml
VGA/data/GRWSurface2018/surface.yaml
VGA/data/GRWSurface2018/uq.yaml
VGA/data/GRWSurface2019/library.yaml
VGA/data/GRWSurface2019/scheme.yaml
VGA/data/GRWSurface2019/surface.yaml
VGA/data/GRWSurface2019/uq.yaml
VGA/data/GuSolventGA2017Aq/library.yaml
VGA/data/GuSolventGA2017Aq/scheme.yaml
VGA/data/GuSolventGA2017Aq/surface.yaml
VGA/data/GuSolventGA2017Aq/uq.yaml
VGA/data/GuSolventGA2017Vac/library.yaml
VGA-1.3.6.dist-info/LICENSE.md
VGA-1.3.6.dist-info/METADATA
VGA-1.3.6.dist-info/WHEEL
VGA-1.3.6.dist-info/dependency_links.txt
VGA-1.3.6.dist-info/top_level.txt
VGA-1.3.6.dist-info/zip-safe
VGA-1.3.6.dist-info/RECORD
