Metadata-Version: 2.1
Name: VGA
Version: 1.3.6
Summary: Python package implements the Group Additivity (GA) method for estimating thermodynamic properties
Home-page: https://github.com/VlachosGroup/VlachosGroupAdditivity
Author: Vlachos Research Group
Author-email: vlachos@udel.edu
License: UNKNOWN
Platform: UNKNOWN
Classifier: Programming Language :: Python :: 3
Classifier: License :: OSI Approved :: MIT License
Classifier: Operating System :: OS Independent
Classifier: Intended Audience :: Science/Research
Classifier: Topic :: Scientific/Engineering :: Chemistry
Requires-Dist: pMuTT (>=1.2.5)
Requires-Dist: scipy (>=1.1.0)
Requires-Dist: numpy (>=1.15.1)
Requires-Dist: IPython (>=7.0.0)
Requires-Dist: PyYAML (>=3.0)
